LICENSE.txt
MANIFEST.in
README.md
setup.cfg
setup.py
certbot_acm/__init__.py
certbot_acm/installer.py
certbot_acm.egg-info/PKG-INFO
certbot_acm.egg-info/SOURCES.txt
certbot_acm.egg-info/dependency_links.txt
certbot_acm.egg-info/entry_points.txt
certbot_acm.egg-info/requires.txt
certbot_acm.egg-info/top_level.txt