Metadata-Version: 1.0
Name: certbot-acm
Version: 0.0.1
Summary: ACM installer plugin for Certbot client
Home-page: https://github.com/selu/certbot-acm
Author: Szabolcs Seláf
Author-email: selu@selu.org
License: MIT
Keywords: certbot,acm
Platform: UNKNOWN
